Workbook

Sheet Instrucciones
B2: UNIVERSIDAD DE VALPARAÍSO · CIN 421 / INF423 — Prueba de Sistemas · 2° Semestre 2026
B3: Plantilla · Matriz de Riesgos
B4: Proyecto TicketU · un archivo por grupo QA y microservicio · Entrega 1
B6: Grupo QA | C6: Grupo 6 (Tablero GitHub Projects) / Módulo 3 (Frontend)
B7: Microservicio | C7: Entradas / Inventario
B8: Equipo TITEC | C8: Renato Herrera, Felipe Castro, Sebastián Fuentes, Esteban Quinteros, Bastián Parra (QA)
B9: Versión / entrega | C9: v1.0 / Entrega 1 (Sprint 1)
B10: Fecha | C10: 02/10/2026
B12: Cómo usarla
B13: 1. Identificar | C13: En «Registro de riesgos», escriban un riesgo por fila: al menos 8 de producto y 3 de proyecto. Fuentes: requisitos, historias de usuario, contrato OpenAPI y estrategia del grupo.
B14: 2. Evaluar | C14: Asignen Probabilidad e Impacto de 1 a 3 según la hoja «Escalas», con acuerdo de todo el grupo.
B15: 3. Calcular | C15: Nivel (P × I), Clasificación e Importancia TestLink se calculan solos: no editen las celdas grises.
B16: 4. Responder | C16: Elijan la respuesta (Mitigar con pruebas, Aceptar, Transferir, Plan de contingencia) y escriban la técnica o acción concreta.
B17: 5. Priorizar | C17: Definan el orden de ejecución: primero los altos, respetando dependencias técnicas y lógicas.
B18: 6. Trazar | C18: Anoten el requisito o HU de origen y los IDs de los casos de TestLink que cubren cada riesgo.
B19: 7. Monitorear | C19: Actualicen Estado y Revisión en cada entrega. Las hojas «Matriz 3x3» y «Resumen» se actualizan solas.
B21: Leyenda
B22: Celda amarilla | C22: Para completar por el grupo.
B23: Celda gris | C23: Fórmula: se calcula sola, no editar.
B24: Alto (6–9) | C24: Clasificación por nivel de riesgo (convención del curso).
B25: Medio (3–4) | C25: Clasificación por nivel de riesgo (convención del curso).
B26: Bajo (1–2) | C26: Clasificación por nivel de riesgo (convención del curso).
B28: Fuentes: ISTQB CTFL 5.5, ISTQB Agile Tester 3.2.1 y Crispin & Gregory, Agile Testing, cap. 18. El curso usa una escala 1–3 por simplicidad.

Sheet Escalas
B2: Escalas de evaluación
B3: Acuerden en el grupo qué significa cada valor antes de puntuar.
B5: Probabilidad: ¿qué tan probable es que falle?
B6: Valor | C6: Nivel | D6: Criterio
B7: 1 | C7: Baja | D7: Regla simple, código estable, sin integraciones.
B8: 2 | C8: Media | D8: Regla con varias condiciones o código cambiado recientemente.
B9: 3 | C9: Alta | D9: Regla compleja, código nuevo, integraciones o mensajes asíncronos, tecnología nueva para el equipo.
B11: Impacto: ¿cuánto daño hace si falla?
B12: Valor | C12: Nivel | D12: Criterio
B13: 1 | C13: Bajo | D13: Molestia menor con alternativa; no afecta dinero ni acceso al evento.
B14: 2 | C14: Medio | D14: Afecta a un grupo de usuarios o una función importante con alternativa difícil.
B15: 3 | C15: Alto | D15: Dinero mal cobrado, asistentes sin poder entrar, datos personales expuestos o reputación del evento.
B17: Nivel = Probabilidad × Impacto
B18: Rango | C18: Clasificación | D18: Qué implica (profundidad de prueba)
B19: 6 a 9 | C19: Alto | D19: Primero y a fondo: varias técnicas, positivos y negativos, retest obligatorio, también en E2E. Importancia Alta en TestLink.
B20: 3 a 4 | C20: Medio | D20: Técnica principal y valores límite; se ejecuta después de los altos. Importancia Media.
B21: 1 a 2 | C21: Bajo | D21: Pocos casos o smoke; se puede aceptar y documentar. Importancia Baja.
B23: Respuesta al riesgo
B24: Respuesta | D24: Cuándo usarla
B25: Mitigar con pruebas | D25: Casos que detecten la falla y reduzcan su probabilidad o su impacto. Respuesta esperada para riesgos de producto alto y medio.
B26: Aceptar | D26: Riesgo bajo: se documenta y se prueba lo mínimo.
B27: Transferir | D27: Otro lo asume o lo comparte (otro grupo QA, equipo plataforma, otra entrega). Indiquen quién.
B28: Plan de contingencia | D28: Qué hará el grupo si el riesgo ocurre. Habitual en riesgos de proyecto.

Sheet Registro de riesgos
A1: Registro de riesgos · Entradas / Inventario · Grupo 6
A2: Amarillo: completar · Gris: fórmula (no editar) · Escala 1–3 (hoja «Escalas»)
A4: ID | B4: Tipo | C4: Riesgo (qué podría fallar) | D4: Requisito / HU | E4: Causa o condición | F4: Prob. (1-3) | G4: Impacto (1-3) | H4: Nivel P×I | I4: Clasificación | J4: Respuesta | K4: Técnica o acción | L4: Orden de ejecución | M4: Casos TestLink | N4: Importancia TestLink | O4: Responsable | P4: Estado | Q4: Revisión (entrega)
A5: R1 | B5: Producto | C5: Entradas huérfanas si falla la comunicación con Check-in al emitir el código QR (POST /api/v1/checkin/tickets). | D5: HU-05 / Contrato enviar_qr_generado v2.1 | E5: Caída temporal o timeout del servicio de Check-in (errores HTTP 500/503) tras descontar el stock en Entradas. | F5: 2 | G5: 3 | H5: =IF(OR(F5="",G5=""),"",F5*G5) | I5: =IF(H5="","",IF(H5>=6,"Alto",IF(H5>=3,"Medio","Bajo"))) | J5: Mitigar con pruebas | K5: Tabla de decisión validando el mecanismo de reintento automático ante errores 500/503 sin bloquear la compra del cliente. | L5: 3 | M5: CP-15, CP-E2E-01, CP-E2E-02 | N5: =IF(I5="","",IF(I5="Alto","Alta",IF(I5="Medio","Media","Baja"))) | O5: Bastián Parra / Sebastián Fuentes | P5: En mitigación | Q5: Entrega 1
A6: R2 | B6: Producto | C6: Incompatibilidad al leer el código QR en puerta por estructura incorrecta del campo qr_data. | D6: HU-05 / Contrato enviar_qr_generado v2.1 | E6: Envío o persistencia de qr_data como string plano o sin las llaves obligatorias (id_evento e id_entrada) exigidas por regla de negocio. | F6: 2 | G6: 3 | H6: =IF(OR(F6="",G6=""),"",F6*G6) | I6: =IF(H6="","",IF(H6>=6,"Alto",IF(H6>=3,"Medio","Bajo"))) | J6: Mitigar con pruebas | K6: Partición de equivalencia validando por contrato que qr_data sea un objeto JSON estricto con id_evento e id_entrada obligatorios. | L6: 1 | M6: CP-12, CP-13, CP-E2E-01, CP-E2E-02 | N6: =IF(I6="","",IF(I6="Alto","Alta",IF(I6="Medio","Media","Baja"))) | O6: Bastián Parra / Renato Herrera | P6: En mitigación | Q6: Entrega 1
A7: R3 | B7: Producto | C7: Filas y demoras en el acceso al evento por lentitud en GET /api/v1/entradas/{id_entrada} o en el registro de QR. | D7: HU-04 / Contrato consultar_entrada v1.0 | E7: Consultas cruzadas entre colecciones para obtener id_evento y nombre_usuario o tiempos de respuesta que superan el SLA (< 300 ms / < 500 ms). | F7: 2 | G7: 3 | H7: =IF(OR(F7="",G7=""),"",F7*G7) | I7: =IF(H7="","",IF(H7>=6,"Alto",IF(H7>=3,"Medio","Bajo"))) | J7: Mitigar con pruebas | K7: Persistir id_evento y nombre_usuario directamente en la colección entrada y aplicar análisis de valores límite al SLA (< 500 ms) en Postman. | L7: 4 | M7: CP-11, CP-12, CP-E2E-01, CP-E2E-02 | N7: =IF(I7="","",IF(I7="Alto","Alta",IF(I7="Medio","Media","Baja"))) | O7: Bastián Parra / Esteban Quinteros | P7: En mitigación | Q7: Entrega 1
A8: R4 | B8: Producto | C8: Sobreventa de cupos o fallo al emitir la solicitud de notificación cuando stock_actual llega a cero. | D8: HU-01, HU-02, HU-03, HU-07 | E8: Descuento de stock en inventario_evento sin validar límite inferior cero o fallo al disparar la alerta hacia Notificaciones al agotarse. | F8: 2 | G8: 3 | H8: =IF(OR(F8="",G8=""),"",F8*G8) | I8: =IF(H8="","",IF(H8>=6,"Alto",IF(H8>=3,"Medio","Bajo"))) | J8: Mitigar con pruebas | K8: Análisis de valores límite sobre el descuento de la última unidad disponible (stock_actual pasa de 1 a 0 vs. de 2 a 1). | L8: 2 | M8: CP-01, CP-03, CP-16, CP-17, CP-E2E-02 | N8: =IF(I8="","",IF(I8="Alto","Alta",IF(I8="Medio","Media","Baja"))) | O8: Bastián Parra / Felipe Castro | P8: Abierto | Q8: Entrega 1
A9: R5 | B9: Producto | C9: Omisión del campo estado_entrada o alteración de datos históricos en la consulta GET /api/v1/entradas/{id_entrada}. | D9: HU-04 / Contrato consultar_entrada v1.0 | E9: El serializador del endpoint no devuelve el estado actual del ticket en el JSON o no garantiza la inmutabilidad de precio_final_pagado y tipo_acceso. | F9: 3 | G9: 3 | H9: =IF(OR(F9="",G9=""),"",F9*G9) | I9: =IF(H9="","",IF(H9>=6,"Alto",IF(H9>=3,"Medio","Bajo"))) | J9: Mitigar con pruebas | K9: Partición de equivalencia y revisión de contrato en Postman verificando la presencia de estado_entrada, precio_final_pagado y tipo_acceso. | L9: 5 | M9: CP-08, CP-E2E-02 | N9: =IF(I9="","",IF(I9="Alto","Alta",IF(I9="Medio","Media","Baja"))) | O9: Bastián Parra / Esteban Quinteros | P9: Materializado | Q9: Entrega 1
A10: R6 | B10: Producto | C10: Emisión anticipada de la entrada y su código QR sin contar con la confirmación de pago exitoso en el flujo pagado. | D10: HU-05, HU-09 | E10: Error en la transición de estados de reserva_entrada que consolida la entrada antes de recibir la aprobación del Microservicio de Pagos. | F10: 2 | G10: 3 | H10: =IF(OR(F10="",G10=""),"",F10*G10) | I10: =IF(H10="","",IF(H10>=6,"Alto",IF(H10>=3,"Medio","Bajo"))) | J10: Mitigar con pruebas | K10: Transición de estados asegurando que en eventos pagados el QR y el envío a Check-in solo ocurran tras confirmar id_pago aprobado. | L10: 6 | M10: CP-20, CP-E2E-02 | N10: =IF(I10="","",IF(I10="Alto","Alta",IF(I10="Medio","Media","Baja"))) | O10: Sebastián Fuentes / Esteban Quinteros | P10: Abierto | Q10: Entrega 1
A11: R7 | B11: Producto | C11: No liberación automática de los cupos reservados temporalmente (holdId) cuando vence el tiempo límite sin pago. | D11: HU-03 | E11: Fallo en el control de fecha_expiracion en reserva_entrada cuando el cliente abandona el proceso de checkout. | F11: 2 | G11: 2 | H11: =IF(OR(F11="",G11=""),"",F11*G11) | I11: =IF(H11="","",IF(H11>=6,"Alto",IF(H11>=3,"Medio","Bajo"))) | J11: Mitigar con pruebas | K11: Transición de estados verificando que al cumplirse fecha_expiracion el estado pase a EXPIRADA y la unidad vuelva al pool de stock_actual. | L11: 7 | M11: CP-05, CP-06 | N11: =IF(I11="","",IF(I11="Alto","Alta",IF(I11="Medio","Media","Baja"))) | O11: Renato Herrera / Bastián Parra | P11: Abierto | Q11: Entrega 1
A12: R8 | B12: Producto | C12: Datos incompletos hacia Check-in por falta de persistencia de nombre_usuario e id_evento en las colecciones de MongoDB. | D12: HU-03, HU-04, HU-05 | E12: Omisión de los atributos obligatorios nombre_usuario e id_evento al insertar documentos en reserva_entrada y entrada. | F12: 2 | G12: 2 | H12: =IF(OR(F12="",G12=""),"",F12*G12) | I12: =IF(H12="","",IF(H12>=6,"Alto",IF(H12>=3,"Medio","Bajo"))) | J12: Mitigar con pruebas | K12: Partición de equivalencia comprobando el rechazo HTTP 400 si falta nombre_usuario y su persistencia en base de datos. | L12: 8 | M12: CP-05, CP-07, CP-08, CP-12 | N12: =IF(I12="","",IF(I12="Alto","Alta",IF(I12="Medio","Media","Baja"))) | O12: Renato Herrera / Bastián Parra | P12: En mitigación | Q12: Entrega 1
A13: R9 | B13: Producto | C13: Superación del límite máximo de entradas gratuitas por usuario (maximo_ticket) o selección de cantidad inválida. | D13: HU-02, HU-08 | E13: Falta de validación de frontera contra maximo_ticket en eventos gratuitos o aceptación de cantidad_entrada <= 0. | F13: 2 | G13: 2 | H13: =IF(OR(F13="",G13=""),"",F13*G13) | I13: =IF(H13="","",IF(H13>=6,"Alto",IF(H13>=3,"Medio","Bajo"))) | J13: Mitigar con pruebas | K13: Análisis de valores límite sobre cantidad_entrada (0, 1, maximo_ticket y maximo_ticket + 1). | L13: 9 | M13: CP-03, CP-04, CP-18, CP-19, CP-E2E-01 | N13: =IF(I13="","",IF(I13="Alto","Alta",IF(I13="Medio","Media","Baja"))) | O13: Felipe Castro / Bastián Parra | P13: Abierto | Q13: Entrega 1
A14: R10 | B14: Producto | C14: Reintentos infinitos o duplicación de registros cuando Check-in responde 409 Conflict ante un ticket ya registrado. | D14: HU-05 / Contrato enviar_qr_generado v2.1 | E14: El manejador de respuestas de Entradas trata el código HTTP 409 igual que un error 500/503 en lugar de detener los reintentos. | F14: 2 | G14: 2 | H14: =IF(OR(F14="",G14=""),"",F14*G14) | I14: =IF(H14="","",IF(H14>=6,"Alto",IF(H14>=3,"Medio","Bajo"))) | J14: Mitigar con pruebas | K14: Tabla de decisión verificando que ante respuesta HTTP 409 Conflict se marque la entrada como sincronizada y no se reintente. | L14: 10 | M14: CP-14 | N14: =IF(I14="","",IF(I14="Alto","Alta",IF(I14="Medio","Media","Baja"))) | O14: Sebastián Fuentes / Bastián Parra | P14: Abierto | Q14: Entrega 1
A15: R11 | B15: Producto | C15: Manejo incorrecto de consultas con id_evento o id_entrada inexistentes o malformados (errores 400 y 404). | D15: HU-01, HU-04 / Contrato consultar_entrada v1.0 | E15: Excepciones no controladas (error 500) cuando se consulta un evento sin inventario o un id_entrada que no existe o tiene formato inválido. | F15: 2 | G15: 2 | H15: =IF(OR(F15="",G15=""),"",F15*G15) | I15: =IF(H15="","",IF(H15>=6,"Alto",IF(H15>=3,"Medio","Bajo"))) | J15: Mitigar con pruebas | K15: Partición de equivalencia con clases inválidas para verificar respuestas controladas HTTP 404 Not Found y HTTP 400 Bad Request. | L15: 11 | M15: CP-02, CP-09, CP-10 | N15: =IF(I15="","",IF(I15="Alto","Alta",IF(I15="Medio","Media","Baja"))) | O15: Esteban Quinteros / Bastián Parra | P15: En mitigación | Q15: Entrega 1
A16: R12 | B16: Producto | C16: Fallo en la emisión síncrona de la entrada y su código QR al confirmar una reserva en el flujo de evento gratuito. | D16: HU-03, HU-05 | E16: El sistema deja la reserva gratuita en espera de confirmación de pago en vez de generar la entrada y enviar el QR de inmediato. | F16: 2 | G16: 2 | H16: =IF(OR(F16="",G16=""),"",F16*G16) | I16: =IF(H16="","",IF(H16>=6,"Alto",IF(H16>=3,"Medio","Bajo"))) | J16: Mitigar con pruebas | K16: Transición de estados en flujo gratuito validando descuento inmediato de stock, creación de entrada y POST a Check-in. | L16: 12 | M16: CP-12, CP-18, CP-E2E-01 | N16: =IF(I16="","",IF(I16="Alto","Alta",IF(I16="Medio","Media","Baja"))) | O16: Esteban Quinteros / Sebastián Fuentes | P16: Abierto | Q16: Entrega 1
... A24: R20 | B24: Proyecto | C24: Descoordinación en el uso de herramientas de gestión QA por no cursar el responsable de pruebas la asignatura Prueba de Sistemas. | D24: Gestión de pruebas (Entregas 1 a 3) | E24: Diferencias de formato en reportes de TestLink/Mantis o concentración de carga de documentación en fechas de entrega. | F24: 2 | G24: 1 | H24: =IF(OR(F24="",G24=""),"",F24*G24) | I24: =IF(H24="","",IF(H24>=6,"Alto",IF(H24>=3,"Medio","Bajo"))) | J24: Plan de contingencia | K24: Repartir la dedicación al 25% entre los integrantes del equipo TITEC y apoyar colaborativamente la carga en TestLink y Matriz de Riesgos. | L24: 20 | M24: N/A (Proyecto) | N24: =IF(I24="","",IF(I24="Alto","Alta",IF(I24="Medio","Media","Baja"))) | O24: Sebastián Fuentes / Equipo Grupo 6 | P24: En mitigación | Q24: Entrega 1
A25: R21 | H25: =IF(OR(F25="",G25=""),"",F25*G25) | I25: =IF(H25="","",IF(H25>=6,"Alto",IF(H25>=3,"Medio","Bajo"))) | N25: =IF(I25="","",IF(I25="Alto","Alta",IF(I25="Medio","Media","Baja")))
A26: R22 | H26: =IF(OR(F26="",G26=""),"",F26*G26) | I26: =IF(H26="","",IF(H26>=6,"Alto",IF(H26>=3,"Medio","Bajo"))) | N26: =IF(I26="","",IF(I26="Alto","Alta",IF(I26="Medio","Media","Baja")))
A27: R23 | H27: =IF(OR(F27="",G27=""),"",F27*G27) | I27: =IF(H27="","",IF(H27>=6,"Alto",IF(H27>=3,"Medio","Bajo"))) | N27: =IF(I27="","",IF(I27="Alto","Alta",IF(I27="Medio","Media","Baja")))
A28: R24 | H28: =IF(OR(F28="",G28=""),"",F28*G28) | I28: =IF(H28="","",IF(H28>=6,"Alto",IF(H28>=3,"Medio","Bajo"))) | N28: =IF(I28="","",IF(I28="Alto","Alta",IF(I28="Medio","Media","Baja")))
A29: R25 | H29: =IF(OR(F29="",G29=""),"",F29*G29) | I29: =IF(H29="","",IF(H29>=6,"Alto",IF(H29>=3,"Medio","Bajo"))) | N29: =IF(I29="","",IF(I29="Alto","Alta",IF(I29="Medio","Media","Baja")))
A30: R26 | H30: =IF(OR(F30="",G30=""),"",F30*G30) | I30: =IF(H30="","",IF(H30>=6,"Alto",IF(H30>=3,"Medio","Bajo"))) | N30: =IF(I30="","",IF(I30="Alto","Alta",IF(I30="Medio","Media","Baja")))
A31: R27 | H31: =IF(OR(F31="",G31=""),"",F31*G31) | I31: =IF(H31="","",IF(H31>=6,"Alto",IF(H31>=3,"Medio","Bajo"))) | N31: =IF(I31="","",IF(I31="Alto","Alta",IF(I31="Medio","Media","Baja")))
A32: R28 | H32: =IF(OR(F32="",G32=""),"",F32*G32) | I32: =IF(H32="","",IF(H32>=6,"Alto",IF(H32>=3,"Medio","Bajo"))) | N32: =IF(I32="","",IF(I32="Alto","Alta",IF(I32="Medio","Media","Baja")))
A33: R29 | H33: =IF(OR(F33="",G33=""),"",F33*G33) | I33: =IF(H33="","",IF(H33>=6,"Alto",IF(H33>=3,"Medio","Bajo"))) | N33: =IF(I33="","",IF(I33="Alto","Alta",IF(I33="Medio","Media","Baja")))
A34: R30 | H34: =IF(OR(F34="",G34=""),"",F34*G34) | I34: =IF(H34="","",IF(H34>=6,"Alto",IF(H34>=3,"Medio","Bajo"))) | N34: =IF(I34="","",IF(I34="Alto","Alta",IF(I34="Medio","Media","Baja")))
A35: R31 | H35: =IF(OR(F35="",G35=""),"",F35*G35) | I35: =IF(H35="","",IF(H35>=6,"Alto",IF(H35>=3,"Medio","Bajo"))) | N35: =IF(I35="","",IF(I35="Alto","Alta",IF(I35="Medio","Media","Baja")))
A36: R32 | H36: =IF(OR(F36="",G36=""),"",F36*G36) | I36: =IF(H36="","",IF(H36>=6,"Alto",IF(H36>=3,"Medio","Bajo"))) | N36: =IF(I36="","",IF(I36="Alto","Alta",IF(I36="Medio","Media","Baja")))
... A44: R40 | H44: =IF(OR(F44="",G44=""),"",F44*G44) | I44: =IF(H44="","",IF(H44>=6,"Alto",IF(H44>=3,"Medio","Bajo"))) | N44: =IF(I44="","",IF(I44="Alto","Alta",IF(I44="Medio","Media","Baja")))

Sheet Matriz 3x3
B2: Matriz de riesgos 3 × 3
B3: Se calcula desde el «Registro de riesgos». Cada celda muestra el nivel (P × I) y la cantidad de riesgos.
B5: Prob. \ Impacto | C5: Bajo (1) | D5: Medio (2) | E5: Alto (3)
B6: Alta (3) | C6: ="3 · Medio"&CHAR(10)&COUNTIFS('Registro de riesgos'!$F$5:$F$44,3,'Registro de riesgos'!$G$5:$G$44,1)&" riesgo(s)" | D6: ="6 · Alto"&CHAR(10)&COUNTIFS('Registro de riesgos'!$F$5:$F$44,3,'Registro de riesgos'!$G$5:$G$44,2)&" riesgo(s)" | E6: ="9 · Alto"&CHAR(10)&COUNTIFS('Registro de riesgos'!$F$5:$F$44,3,'Registro de riesgos'!$G$5:$G$44,3)&" riesgo(s)" | G6: Alto | H6: 6–9 · primero y a fondo
B7: Media (2) | C7: ="2 · Bajo"&CHAR(10)&COUNTIFS('Registro de riesgos'!$F$5:$F$44,2,'Registro de riesgos'!$G$5:$G$44,1)&" riesgo(s)" | D7: ="4 · Medio"&CHAR(10)&COUNTIFS('Registro de riesgos'!$F$5:$F$44,2,'Registro de riesgos'!$G$5:$G$44,2)&" riesgo(s)" | E7: ="6 · Alto"&CHAR(10)&COUNTIFS('Registro de riesgos'!$F$5:$F$44,2,'Registro de riesgos'!$G$5:$G$44,3)&" riesgo(s)" | G7: Medio | H7: 3–4 · técnica principal
B8: Baja (1) | C8: ="1 · Bajo"&CHAR(10)&COUNTIFS('Registro de riesgos'!$F$5:$F$44,1,'Registro de riesgos'!$G$5:$G$44,1)&" riesgo(s)" | D8: ="2 · Bajo"&CHAR(10)&COUNTIFS('Registro de riesgos'!$F$5:$F$44,1,'Registro de riesgos'!$G$5:$G$44,2)&" riesgo(s)" | E8: ="3 · Medio"&CHAR(10)&COUNTIFS('Registro de riesgos'!$F$5:$F$44,1,'Registro de riesgos'!$G$5:$G$44,3)&" riesgo(s)" | G8: Bajo | H8: 1–2 · mínimo o smoke
B10: Impacto → · ↑ Probabilidad

Sheet Resumen
B2: Resumen por clasificación y tipo
B4: Clasificación | C4: Producto | D4: Proyecto | E4: Total
B5: Alto | C5: =COUNTIFS('Registro de riesgos'!$I$5:$I$44,"Alto",'Registro de riesgos'!$B$5:$B$44,"Producto") | D5: =COUNTIFS('Registro de riesgos'!$I$5:$I$44,"Alto",'Registro de riesgos'!$B$5:$B$44,"Proyecto") | E5: =C5+D5
B6: Medio | C6: =COUNTIFS('Registro de riesgos'!$I$5:$I$44,"Medio",'Registro de riesgos'!$B$5:$B$44,"Producto") | D6: =COUNTIFS('Registro de riesgos'!$I$5:$I$44,"Medio",'Registro de riesgos'!$B$5:$B$44,"Proyecto") | E6: =C6+D6
B7: Bajo | C7: =COUNTIFS('Registro de riesgos'!$I$5:$I$44,"Bajo",'Registro de riesgos'!$B$5:$B$44,"Producto") | D7: =COUNTIFS('Registro de riesgos'!$I$5:$I$44,"Bajo",'Registro de riesgos'!$B$5:$B$44,"Proyecto") | E7: =C7+D7
B8: Total | C8: =SUM(C5:C7) | D8: =SUM(D5:D7) | E8: =SUM(E5:E7)
B10: Mínimo para la Entrega 1
B11: Riesgos de producto | C11: =C8 | D11: =IF(C11>=8,"OK","Falta") | E11: Meta: ≥ 8
B12: Riesgos de proyecto | C12: =D8 | D12: =IF(C12>=3,"OK","Falta") | E12: Meta: ≥ 3
B13: Altos/medios sin respuesta | C13: =COUNTIFS('Registro de riesgos'!$I$5:$I$44,"Alto",'Registro de riesgos'!$J$5:$J$44,"")+COUNTIFS('Registro de riesgos'!$I$5:$I$44,"Medio",'Registro de riesgos'!$J$5:$J$44,"") | D13: =IF(C13=0,"OK","Falta") | E13: Meta: 0
B14: Altos de producto sin casos TestLink | C14: =COUNTIFS('Registro de riesgos'!$I$5:$I$44,"Alto",'Registro de riesgos'!$B$5:$B$44,"Producto",'Registro de riesgos'!$M$5:$M$44,"") | D14: =IF(C14=0,"OK","Falta") | E14: Meta: 0
